MANIFEST.in
README
_version.py
setup.cfg
setup.py
pyrant/__init__.py
pyrant/exceptions.py
pyrant/protocol.py
pyrant/query.py
pyrant/ttserver.py
pyrant.egg-info/PKG-INFO
pyrant.egg-info/SOURCES.txt
pyrant.egg-info/dependency_links.txt
pyrant.egg-info/requires.txt
pyrant.egg-info/top_level.txt
pyrant/utils/__init__.py
pyrant/utils/django.py