Metadata-Version: 1.0
Name: pyrant
Version: 0.6.5
Summary: A python wrapper around Tokyo Tyrant
Home-page: http://code.google.com/p/pyrant/
Author: Andrey Mikhaylenko
Author-email: andy@neithere.net
License: Apache License 2.0
Platform: UNKNOWN
Classifier: Intended Audience :: Developers
Classifier: Development Status :: 4 - Beta
Classifier: Programming Language :: Python
Classifier: Intended Audience :: Developers
Classifier: License :: OSI Approved :: Apache Software License
Classifier: Topic :: Software Development :: Libraries :: Python Modules
Classifier: Topic :: Database :: Front-Ends
